[
    {
        "title": "Autonomy\u2019s Mike Lynch acquitted after US fraud trial brought by HP",
        "link": "https://techcrunch.com/2024/06/07/autonomys-mike-lynch-acquitted-after-us-fraud-trial-brought-by-hp/",
        "timeposted": "2024-06-08 02:57:17"
    },
    {
        "title": "What Snowflake isn\u2019t saying about its customer data breaches",
        "link": "https://techcrunch.com/2024/06/07/snowflake-ticketmaster-lendingtree-customer-data-breach/",
        "timeposted": "2024-06-08 02:57:17"
    },
    {
        "title": "Rippling bans former employees who work at competitors like Deel and Workday from its tender offer stock sale",
        "link": "https://techcrunch.com/2024/06/07/rippling-former-employees-competitors-deel-workday-tender-offer-stock-sale/",
        "timeposted": "2024-06-07 23:57:17"
    },
    {
        "title": "NASA puts $10M down on Mars sample return proposals from Blue Origin, SpaceX and others",
        "link": "https://techcrunch.com/2024/06/07/nasa-puts-10m-down-on-mars-sample-return-proposals-from-blue-origin-spacex-and-others/",
        "timeposted": "2024-06-07 23:57:17"
    }
]